.travis.yml
LICENSE
MANIFEST.in
README.rst
setup.cfg
setup.py
tox.ini
Mopidy_GPIOcont.egg-info/PKG-INFO
Mopidy_GPIOcont.egg-info/SOURCES.txt
Mopidy_GPIOcont.egg-info/dependency_links.txt
Mopidy_GPIOcont.egg-info/entry_points.txt
Mopidy_GPIOcont.egg-info/not-zip-safe
Mopidy_GPIOcont.egg-info/requires.txt
Mopidy_GPIOcont.egg-info/top_level.txt
mopidy_gpiocont/I2C_LCD_driver.py
mopidy_gpiocont/__init__.py
mopidy_gpiocont/commands.py
mopidy_gpiocont/ext.conf
mopidy_gpiocont/frontend.py
mopidy_gpiocont/in_gpio.py
tests/__init__.py
tests/test_extension.py