Metadata-Version: 1.1
Name: Mopidy-GPIOcont
Version: 0.2.2
Summary: Extension to control musicbox via gpio.
Home-page: https://github.com/jaspergerth/mopidy-gpiocont
Author: Jasper Gerth
Author-email: jaspergerth@gmail.com
License: Apache License, Version 2.0
Platform: UNKNOWN
Classifier: Environment :: No Input/Output (Daemon)
Classifier: Intended Audience :: End Users/Desktop
Classifier: License :: OSI Approved :: Apache Software License
Classifier: Operating System :: OS Independent
Classifier: Programming Language :: Python :: 2
Classifier: Topic :: Multimedia :: Sound/Audio :: Players
